docs/conf.py
opensmile/__init__.py
opensmile/core/__init__.py
opensmile/core/config.py
opensmile/core/define.py
opensmile/core/lib.py
opensmile/core/smile.py
opensmile/core/bin/macosx_11_0_arm64/libSMILEapi.dylib
opensmile/core/config/compare/ComParE_2016.conf
opensmile/core/config/compare/ComParE_2016_core.func.conf.inc
opensmile/core/config/compare/ComParE_2016_core.lld.conf.inc
opensmile/core/config/compare/basic_functionals_2016.conf.inc
opensmile/core/config/egemaps/v01a/eGeMAPSv01a.conf
opensmile/core/config/egemaps/v01a/eGeMAPSv01a_core.func.conf.inc
opensmile/core/config/egemaps/v01a/eGeMAPSv01a_core.lld.conf.inc
opensmile/core/config/egemaps/v01b/eGeMAPSv01b.conf
opensmile/core/config/egemaps/v01b/eGeMAPSv01b_core.func.conf.inc
opensmile/core/config/egemaps/v01b/eGeMAPSv01b_core.lld.conf.inc
opensmile/core/config/egemaps/v02/eGeMAPSv02.conf
opensmile/core/config/egemaps/v02/eGeMAPSv02_core.func.conf.inc
opensmile/core/config/egemaps/v02/eGeMAPSv02_core.lld.conf.inc
opensmile/core/config/emobase/emobase.conf
opensmile/core/config/gemaps/v01a/GeMAPSv01a.conf
opensmile/core/config/gemaps/v01a/GeMAPSv01a_core.func.conf.inc
opensmile/core/config/gemaps/v01a/GeMAPSv01a_core.lld.conf.inc
opensmile/core/config/gemaps/v01b/GeMAPSv01b.conf
opensmile/core/config/gemaps/v01b/GeMAPSv01b_core.func.conf.inc
opensmile/core/config/gemaps/v01b/GeMAPSv01b_core.lld.conf.inc
opensmile/core/config/shared/BufferMode.conf.inc
opensmile/core/config/shared/BufferModeRb.conf.inc
opensmile/core/config/shared/BufferModeRbLag.conf.inc
opensmile/core/config/shared/BufferModeRbMulti.conf.inc
opensmile/core/config/shared/FrameModeFunctionals.conf.inc
opensmile/core/config/shared/FrameModeFunctionalsMulti.conf.inc
opensmile/core/config/shared/standard_data_output.conf.inc
opensmile/core/config/shared/standard_data_output_no_lld_de.conf.inc
opensmile/core/config/shared/standard_external_data_output_multi.conf.inc
opensmile/core/config/shared/standard_external_data_output_single.conf.inc
opensmile-2.5.0.dist-info/LICENSE
opensmile-2.5.0.dist-info/METADATA
opensmile-2.5.0.dist-info/WHEEL
opensmile-2.5.0.dist-info/top_level.txt
opensmile-2.5.0.dist-info/RECORD
