Metadata-Version: 2.1
Name: opensmile
Version: 2.5.0
Summary: Python wrapper for common openSMILE feature sets
Author: Christop Hausner
Author-email: Johannes Wagner <jwagner@audeering.com>, Hagen Wierstorf <hwierstorf@audeering.com>
License:   openSMILE 
Project-URL: repository, https://github.com/audeering/opensmile-python/
Project-URL: documentation, https://audeering.github.io/opensmile-python/
Keywords: audio,tools,feature,opensmile,audeering
Classifier: Development Status :: 5 - Production/Stable
Classifier: Intended Audience :: Science/Research
Classifier: Intended Audience :: Developers
Classifier: License :: OSI Approved :: MIT License
Classifier: Operating System :: OS Independent
Classifier: Programming Language :: Python
Classifier: Programming Language :: Python :: 3
Classifier: Programming Language :: Python :: 3.8
Classifier: Programming Language :: Python :: 3.9
Classifier: Programming Language :: Python :: 3.10
Classifier: Programming Language :: Python :: 3.11
Classifier: Topic :: Scientific/Engineering
License-File: LICENSE
Requires-Dist: audobject>=0.6.1
Requires-Dist: audinterface>=0.7.0
